core/Exchange.py
core/__init__.py
core/account/AccountBalance.py
core/account/__init__.py
core/main.py
core/smc/SMCBase.py
core/smc/SMCFVG.py
core/smc/SMCLiquidity.py
core/smc/SMCOrderBlock.py
core/smc/SMCPDArray.py
core/smc/SMCStruct.py
core/smc/TF.py
core/smc/__init__.py
core/utils/OPTools.py
core/utils/__init__.py
openfund_core-1.1.10.dist-info/METADATA
openfund_core-1.1.10.dist-info/WHEEL
openfund_core-1.1.10.dist-info/entry_points.txt
openfund_core-1.1.10.dist-info/RECORD
