Metadata-Version: 2.3
Name: openfund-core
Version: 1.1.10
Summary: Openfund-core.
Requires-Python: >=3.9,<4.0
Classifier: Programming Language :: Python :: 3
Classifier: Programming Language :: Python :: 3.9
Classifier: Programming Language :: Python :: 3.10
Classifier: Programming Language :: Python :: 3.11
Classifier: Programming Language :: Python :: 3.12
Classifier: Programming Language :: Python :: 3.13
Requires-Dist: apscheduler (>=3.11.0,<4.0.0)
Requires-Dist: ccxt (>=4.4.26,<5.0.0)
Requires-Dist: pandas (>=2.2.3,<3.0.0)
Requires-Dist: pyfiglet (>=1.0.2,<2.0.0)
Requires-Dist: pyyaml (>=6.0.2,<7.0.0)
